{
    "data": {
        "products": {
            "total_count": 37,
            "items": [
                {
                    "productlabel": "",
                    "__typename": "SimpleProduct",
                    "id": 1166,
                    "name": "Sol",
                    "color": 99,
                    "sku": "203154568",
                    "short_description": {
                        "html": "Gold and Beige Straw Patterned Bag"
                    },
                    "small_image": {
                        "url": "https://dev.couturelabs.com/media/catalog/product/cache/b8d8fe45faeda26b4dc07b7dc739a347/1/_/1_20.jpg"
                    },
                    "price_range": {
                        "maximum_price": {
                            "fixed_product_taxes": [],
                            "regular_price": {
                                "currency": "AED",
                                "value": 400
                            },
                            "final_price": {
                                "currency": "AED",
                                "value": 400
                            },
                            "discount": {
                                "amount_off": 0,
                                "percent_off": 0
                            }
                        },
                        "minimum_price": {
                            "fixed_product_taxes": [],
                            "regular_price": {
                                "currency": "AED",
                                "value": 400
                            },
                            "final_price": {
                                "currency": "AED",
                                "value": 400
                            },
                            "discount": {
                                "amount_off": 0,
                                "percent_off": 0
                            }
                        }
                    }
                },
                {
                    "productlabel": "",
                    "__typename": "SimpleProduct",
                    "id": 924,
                    "name": "Seda",
                    "color": 99,
                    "sku": "203154542",
                    "short_description": {
                        "html": "Brown Satchel Bag"
                    },
                    "small_image": {
                        "url": "https://dev.couturelabs.com/media/catalog/product/cache/b8d8fe45faeda26b4dc07b7dc739a347/e/m/emptyname_1157_copy.jpg"
                    },
                    "price_range": {
                        "maximum_price": {
                            "fixed_product_taxes": [],
                            "regular_price": {
                                "currency": "AED",
                                "value": 370
                            },
                            "final_price": {
                                "currency": "AED",
                                "value": 370
                            },
                            "discount": {
                                "amount_off": 0,
                                "percent_off": 0
                            }
                        },
                        "minimum_price": {
                            "fixed_product_taxes": [],
                            "regular_price": {
                                "currency": "AED",
                                "value": 370
                            },
                            "final_price": {
                                "currency": "AED",
                                "value": 370
                            },
                            "discount": {
                                "amount_off": 0,
                                "percent_off": 0
                            }
                        }
                    }
                },
                {
                    "productlabel": "",
                    "__typename": "SimpleProduct",
                    "id": 720,
                    "name": "Lucia",
                    "color": 173,
                    "sku": "203154560",
                    "short_description": {
                        "html": "Brown Shopper Bag"
                    },
                    "small_image": {
                        "url": "https://dev.couturelabs.com/media/catalog/product/cache/b8d8fe45faeda26b4dc07b7dc739a347/p/l/plp_0082_emptyname_46_1.jpg"
                    },
                    "price_range": {
                        "maximum_price": {
                            "fixed_product_taxes": [],
                            "regular_price": {
                                "currency": "AED",
                                "value": 338
                            },
                            "final_price": {
                                "currency": "AED",
                                "value": 338
                            },
                            "discount": {
                                "amount_off": 0,
                                "percent_off": 0
                            }
                        },
                        "minimum_price": {
                            "fixed_product_taxes": [],
                            "regular_price": {
                                "currency": "AED",
                                "value": 338
                            },
                            "final_price": {
                                "currency": "AED",
                                "value": 338
                            },
                            "discount": {
                                "amount_off": 0,
                                "percent_off": 0
                            }
                        }
                    }
                },
                {
                    "productlabel": "",
                    "__typename": "SimpleProduct",
                    "id": 718,
                    "name": "Odina",
                    "color": 173,
                    "sku": "203154558",
                    "short_description": {
                        "html": "Brown Shopper Bag"
                    },
                    "small_image": {
                        "url": "https://dev.couturelabs.com/media/catalog/product/cache/b8d8fe45faeda26b4dc07b7dc739a347/p/l/plp_0065_emptyname_1193.jpg"
                    },
                    "price_range": {
                        "maximum_price": {
                            "fixed_product_taxes": [],
                            "regular_price": {
                                "currency": "AED",
                                "value": 338
                            },
                            "final_price": {
                                "currency": "AED",
                                "value": 338
                            },
                            "discount": {
                                "amount_off": 0,
                                "percent_off": 0
                            }
                        },
                        "minimum_price": {
                            "fixed_product_taxes": [],
                            "regular_price": {
                                "currency": "AED",
                                "value": 338
                            },
                            "final_price": {
                                "currency": "AED",
                                "value": 338
                            },
                            "discount": {
                                "amount_off": 0,
                                "percent_off": 0
                            }
                        }
                    }
                },
                {
                    "productlabel": "",
                    "__typename": "SimpleProduct",
                    "id": 717,
                    "name": "Urika",
                    "color": 173,
                    "sku": "203154557",
                    "short_description": {
                        "html": "Brown Shopper Bag"
                    },
                    "small_image": {
                        "url": "https://dev.couturelabs.com/media/catalog/product/cache/b8d8fe45faeda26b4dc07b7dc739a347/p/l/plp_0061_emptyname_1200.jpg"
                    },
                    "price_range": {
                        "maximum_price": {
                            "fixed_product_taxes": [],
                            "regular_price": {
                                "currency": "AED",
                                "value": 338
                            },
                            "final_price": {
                                "currency": "AED",
                                "value": 338
                            },
                            "discount": {
                                "amount_off": 0,
                                "percent_off": 0
                            }
                        },
                        "minimum_price": {
                            "fixed_product_taxes": [],
                            "regular_price": {
                                "currency": "AED",
                                "value": 338
                            },
                            "final_price": {
                                "currency": "AED",
                                "value": 338
                            },
                            "discount": {
                                "amount_off": 0,
                                "percent_off": 0
                            }
                        }
                    }
                },
                {
                    "productlabel": "",
                    "__typename": "SimpleProduct",
                    "id": 715,
                    "name": "Isabella",
                    "color": 24,
                    "sku": "203154555",
                    "short_description": {
                        "html": "White Shoulder Bag"
                    },
                    "small_image": {
                        "url": "https://dev.couturelabs.com/media/catalog/product/cache/b8d8fe45faeda26b4dc07b7dc739a347/i/s/isabella_1.jpg"
                    },
                    "price_range": {
                        "maximum_price": {
                            "fixed_product_taxes": [],
                            "regular_price": {
                                "currency": "AED",
                                "value": 338
                            },
                            "final_price": {
                                "currency": "AED",
                                "value": 338
                            },
                            "discount": {
                                "amount_off": 0,
                                "percent_off": 0
                            }
                        },
                        "minimum_price": {
                            "fixed_product_taxes": [],
                            "regular_price": {
                                "currency": "AED",
                                "value": 338
                            },
                            "final_price": {
                                "currency": "AED",
                                "value": 338
                            },
                            "discount": {
                                "amount_off": 0,
                                "percent_off": 0
                            }
                        }
                    }
                },
                {
                    "productlabel": "",
                    "__typename": "SimpleProduct",
                    "id": 1169,
                    "name": "Kelly",
                    "color": 107,
                    "sku": "203154572",
                    "short_description": {
                        "html": "Dark Green Squared Fur Bag"
                    },
                    "small_image": {
                        "url": "https://dev.couturelabs.com/media/catalog/product/cache/b8d8fe45faeda26b4dc07b7dc739a347/1/_/1_17.jpg"
                    },
                    "price_range": {
                        "maximum_price": {
                            "fixed_product_taxes": [],
                            "regular_price": {
                                "currency": "AED",
                                "value": 320
                            },
                            "final_price": {
                                "currency": "AED",
                                "value": 320
                            },
                            "discount": {
                                "amount_off": 0,
                                "percent_off": 0
                            }
                        },
                        "minimum_price": {
                            "fixed_product_taxes": [],
                            "regular_price": {
                                "currency": "AED",
                                "value": 320
                            },
                            "final_price": {
                                "currency": "AED",
                                "value": 320
                            },
                            "discount": {
                                "amount_off": 0,
                                "percent_off": 0
                            }
                        }
                    }
                },
                {
                    "productlabel": "",
                    "__typename": "SimpleProduct",
                    "id": 1175,
                    "name": "Finn",
                    "color": 99,
                    "sku": "203154578",
                    "short_description": {
                        "html": "Brown & Cream Straw Bucket Bag"
                    },
                    "small_image": {
                        "url": "https://dev.couturelabs.com/media/catalog/product/cache/b8d8fe45faeda26b4dc07b7dc739a347/1/_/1_11.jpg"
                    },
                    "price_range": {
                        "maximum_price": {
                            "fixed_product_taxes": [],
                            "regular_price": {
                                "currency": "AED",
                                "value": 300
                            },
                            "final_price": {
                                "currency": "AED",
                                "value": 300
                            },
                            "discount": {
                                "amount_off": 0,
                                "percent_off": 0
                            }
                        },
                        "minimum_price": {
                            "fixed_product_taxes": [],
                            "regular_price": {
                                "currency": "AED",
                                "value": 300
                            },
                            "final_price": {
                                "currency": "AED",
                                "value": 300
                            },
                            "discount": {
                                "amount_off": 0,
                                "percent_off": 0
                            }
                        }
                    }
                },
                {
                    "productlabel": "",
                    "__typename": "SimpleProduct",
                    "id": 719,
                    "name": "Buana",
                    "color": 173,
                    "sku": "203154559",
                    "short_description": {
                        "html": "Brown Shopper Bag"
                    },
                    "small_image": {
                        "url": "https://dev.couturelabs.com/media/catalog/product/cache/b8d8fe45faeda26b4dc07b7dc739a347/e/m/emptyname_1214.jpg"
                    },
                    "price_range": {
                        "maximum_price": {
                            "fixed_product_taxes": [],
                            "regular_price": {
                                "currency": "AED",
                                "value": 300
                            },
                            "final_price": {
                                "currency": "AED",
                                "value": 300
                            },
                            "discount": {
                                "amount_off": 0,
                                "percent_off": 0
                            }
                        },
                        "minimum_price": {
                            "fixed_product_taxes": [],
                            "regular_price": {
                                "currency": "AED",
                                "value": 300
                            },
                            "final_price": {
                                "currency": "AED",
                                "value": 300
                            },
                            "discount": {
                                "amount_off": 0,
                                "percent_off": 0
                            }
                        }
                    }
                },
                {
                    "productlabel": "",
                    "__typename": "SimpleProduct",
                    "id": 716,
                    "name": "Halona ",
                    "color": 174,
                    "sku": "203154556",
                    "short_description": {
                        "html": "Multicolor Shoulder Bag"
                    },
                    "small_image": {
                        "url": "https://dev.couturelabs.com/media/catalog/product/cache/b8d8fe45faeda26b4dc07b7dc739a347/p/l/plp_0055_emptyname_1210.jpg"
                    },
                    "price_range": {
                        "maximum_price": {
                            "fixed_product_taxes": [],
                            "regular_price": {
                                "currency": "AED",
                                "value": 250
                            },
                            "final_price": {
                                "currency": "AED",
                                "value": 250
                            },
                            "discount": {
                                "amount_off": 0,
                                "percent_off": 0
                            }
                        },
                        "minimum_price": {
                            "fixed_product_taxes": [],
                            "regular_price": {
                                "currency": "AED",
                                "value": 250
                            },
                            "final_price": {
                                "currency": "AED",
                                "value": 250
                            },
                            "discount": {
                                "amount_off": 0,
                                "percent_off": 0
                            }
                        }
                    }
                },
                {
                    "productlabel": "",
                    "__typename": "SimpleProduct",
                    "id": 713,
                    "name": "Mira",
                    "color": 173,
                    "sku": "203154553",
                    "short_description": {
                        "html": "Brown Backpack Bag"
                    },
                    "small_image": {
                        "url": "https://dev.couturelabs.com/media/catalog/product/cache/b8d8fe45faeda26b4dc07b7dc739a347/p/l/plp_0048_emptyname_1236.jpg"
                    },
                    "price_range": {
                        "maximum_price": {
                            "fixed_product_taxes": [],
                            "regular_price": {
                                "currency": "AED",
                                "value": 240
                            },
                            "final_price": {
                                "currency": "AED",
                                "value": 240
                            },
                            "discount": {
                                "amount_off": 0,
                                "percent_off": 0
                            }
                        },
                        "minimum_price": {
                            "fixed_product_taxes": [],
                            "regular_price": {
                                "currency": "AED",
                                "value": 240
                            },
                            "final_price": {
                                "currency": "AED",
                                "value": 240
                            },
                            "discount": {
                                "amount_off": 0,
                                "percent_off": 0
                            }
                        }
                    }
                },
                {
                    "productlabel": "",
                    "__typename": "SimpleProduct",
                    "id": 1171,
                    "name": "Beta",
                    "color": 113,
                    "sku": "203154574",
                    "short_description": {
                        "html": "Yellow Crocodile Skin Mini Bag"
                    },
                    "small_image": {
                        "url": "https://dev.couturelabs.com/media/catalog/product/cache/b8d8fe45faeda26b4dc07b7dc739a347/1/_/1_7.jpg"
                    },
                    "price_range": {
                        "maximum_price": {
                            "fixed_product_taxes": [],
                            "regular_price": {
                                "currency": "AED",
                                "value": 220
                            },
                            "final_price": {
                                "currency": "AED",
                                "value": 220
                            },
                            "discount": {
                                "amount_off": 0,
                                "percent_off": 0
                            }
                        },
                        "minimum_price": {
                            "fixed_product_taxes": [],
                            "regular_price": {
                                "currency": "AED",
                                "value": 220
                            },
                            "final_price": {
                                "currency": "AED",
                                "value": 220
                            },
                            "discount": {
                                "amount_off": 0,
                                "percent_off": 0
                            }
                        }
                    }
                },
                {
                    "productlabel": "",
                    "__typename": "SimpleProduct",
                    "id": 1170,
                    "name": "Alpha",
                    "color": 25,
                    "sku": "203154573",
                    "short_description": {
                        "html": "Pink Crocodile Skin Mini Bag"
                    },
                    "small_image": {
                        "url": "https://dev.couturelabs.com/media/catalog/product/cache/b8d8fe45faeda26b4dc07b7dc739a347/1/_/1_4_1.jpg"
                    },
                    "price_range": {
                        "maximum_price": {
                            "fixed_product_taxes": [],
                            "regular_price": {
                                "currency": "AED",
                                "value": 220
                            },
                            "final_price": {
                                "currency": "AED",
                                "value": 220
                            },
                            "discount": {
                                "amount_off": 0,
                                "percent_off": 0
                            }
                        },
                        "minimum_price": {
                            "fixed_product_taxes": [],
                            "regular_price": {
                                "currency": "AED",
                                "value": 220
                            },
                            "final_price": {
                                "currency": "AED",
                                "value": 220
                            },
                            "discount": {
                                "amount_off": 0,
                                "percent_off": 0
                            }
                        }
                    }
                },
                {
                    "productlabel": "",
                    "__typename": "SimpleProduct",
                    "id": 1159,
                    "name": "Bruno",
                    "color": 419,
                    "sku": "203154561",
                    "short_description": {
                        "html": "Beige & White Plated Clutch"
                    },
                    "small_image": {
                        "url": "https://dev.couturelabs.com/media/catalog/product/cache/b8d8fe45faeda26b4dc07b7dc739a347/1/_/1_9.jpg"
                    },
                    "price_range": {
                        "maximum_price": {
                            "fixed_product_taxes": [],
                            "regular_price": {
                                "currency": "AED",
                                "value": 220
                            },
                            "final_price": {
                                "currency": "AED",
                                "value": 220
                            },
                            "discount": {
                                "amount_off": 0,
                                "percent_off": 0
                            }
                        },
                        "minimum_price": {
                            "fixed_product_taxes": [],
                            "regular_price": {
                                "currency": "AED",
                                "value": 220
                            },
                            "final_price": {
                                "currency": "AED",
                                "value": 220
                            },
                            "discount": {
                                "amount_off": 0,
                                "percent_off": 0
                            }
                        }
                    }
                },
                {
                    "productlabel": "",
                    "__typename": "SimpleProduct",
                    "id": 714,
                    "name": "Ordina",
                    "color": 173,
                    "sku": "203154554",
                    "short_description": {
                        "html": "Brown Handbag"
                    },
                    "small_image": {
                        "url": "https://dev.couturelabs.com/media/catalog/product/cache/b8d8fe45faeda26b4dc07b7dc739a347/e/m/emptyname_1159.jpg"
                    },
                    "price_range": {
                        "maximum_price": {
                            "fixed_product_taxes": [],
                            "regular_price": {
                                "currency": "AED",
                                "value": 210
                            },
                            "final_price": {
                                "currency": "AED",
                                "value": 210
                            },
                            "discount": {
                                "amount_off": 0,
                                "percent_off": 0
                            }
                        },
                        "minimum_price": {
                            "fixed_product_taxes": [],
                            "regular_price": {
                                "currency": "AED",
                                "value": 210
                            },
                            "final_price": {
                                "currency": "AED",
                                "value": 210
                            },
                            "discount": {
                                "amount_off": 0,
                                "percent_off": 0
                            }
                        }
                    }
                },
                {
                    "productlabel": "",
                    "__typename": "SimpleProduct",
                    "id": 1174,
                    "name": "Pursify",
                    "color": 99,
                    "sku": "203154577",
                    "short_description": {
                        "html": "Brown Weaved Flap Shoulder Bag"
                    },
                    "small_image": {
                        "url": "https://dev.couturelabs.com/media/catalog/product/cache/b8d8fe45faeda26b4dc07b7dc739a347/1/_/1_19.jpg"
                    },
                    "price_range": {
                        "maximum_price": {
                            "fixed_product_taxes": [],
                            "regular_price": {
                                "currency": "AED",
                                "value": 200
                            },
                            "final_price": {
                                "currency": "AED",
                                "value": 200
                            },
                            "discount": {
                                "amount_off": 0,
                                "percent_off": 0
                            }
                        },
                        "minimum_price": {
                            "fixed_product_taxes": [],
                            "regular_price": {
                                "currency": "AED",
                                "value": 200
                            },
                            "final_price": {
                                "currency": "AED",
                                "value": 200
                            },
                            "discount": {
                                "amount_off": 0,
                                "percent_off": 0
                            }
                        }
                    }
                },
                {
                    "productlabel": "",
                    "__typename": "SimpleProduct",
                    "id": 1165,
                    "name": "Ally",
                    "color": 108,
                    "sku": "203154567",
                    "short_description": {
                        "html": "Olive Green Pleated Crescent Bag"
                    },
                    "small_image": {
                        "url": "https://dev.couturelabs.com/media/catalog/product/cache/b8d8fe45faeda26b4dc07b7dc739a347/1/_/1_20_1.jpg"
                    },
                    "price_range": {
                        "maximum_price": {
                            "fixed_product_taxes": [],
                            "regular_price": {
                                "currency": "AED",
                                "value": 200
                            },
                            "final_price": {
                                "currency": "AED",
                                "value": 200
                            },
                            "discount": {
                                "amount_off": 0,
                                "percent_off": 0
                            }
                        },
                        "minimum_price": {
                            "fixed_product_taxes": [],
                            "regular_price": {
                                "currency": "AED",
                                "value": 200
                            },
                            "final_price": {
                                "currency": "AED",
                                "value": 200
                            },
                            "discount": {
                                "amount_off": 0,
                                "percent_off": 0
                            }
                        }
                    }
                },
                {
                    "productlabel": "",
                    "__typename": "SimpleProduct",
                    "id": 1164,
                    "name": "Twig",
                    "color": 99,
                    "sku": "203154566",
                    "short_description": {
                        "html": "Brown Pleated Crescent Bag"
                    },
                    "small_image": {
                        "url": "https://dev.couturelabs.com/media/catalog/product/cache/b8d8fe45faeda26b4dc07b7dc739a347/1/_/1_15.jpg"
                    },
                    "price_range": {
                        "maximum_price": {
                            "fixed_product_taxes": [],
                            "regular_price": {
                                "currency": "AED",
                                "value": 200
                            },
                            "final_price": {
                                "currency": "AED",
                                "value": 200
                            },
                            "discount": {
                                "amount_off": 0,
                                "percent_off": 0
                            }
                        },
                        "minimum_price": {
                            "fixed_product_taxes": [],
                            "regular_price": {
                                "currency": "AED",
                                "value": 200
                            },
                            "final_price": {
                                "currency": "AED",
                                "value": 200
                            },
                            "discount": {
                                "amount_off": 0,
                                "percent_off": 0
                            }
                        }
                    }
                },
                {
                    "productlabel": "",
                    "__typename": "SimpleProduct",
                    "id": 1163,
                    "name": "Frost",
                    "color": 420,
                    "sku": "203154565",
                    "short_description": {
                        "html": "Ivory Pleated Crescent Bag"
                    },
                    "small_image": {
                        "url": "https://dev.couturelabs.com/media/catalog/product/cache/b8d8fe45faeda26b4dc07b7dc739a347/1/_/1_12.jpg"
                    },
                    "price_range": {
                        "maximum_price": {
                            "fixed_product_taxes": [],
                            "regular_price": {
                                "currency": "AED",
                                "value": 200
                            },
                            "final_price": {
                                "currency": "AED",
                                "value": 200
                            },
                            "discount": {
                                "amount_off": 0,
                                "percent_off": 0
                            }
                        },
                        "minimum_price": {
                            "fixed_product_taxes": [],
                            "regular_price": {
                                "currency": "AED",
                                "value": 200
                            },
                            "final_price": {
                                "currency": "AED",
                                "value": 200
                            },
                            "discount": {
                                "amount_off": 0,
                                "percent_off": 0
                            }
                        }
                    }
                },
                {
                    "productlabel": "",
                    "__typename": "SimpleProduct",
                    "id": 1161,
                    "name": "Coal",
                    "color": 21,
                    "sku": "203154563",
                    "short_description": {
                        "html": "Black Quilted Stud Handbag"
                    },
                    "small_image": {
                        "url": "https://dev.couturelabs.com/media/catalog/product/cache/b8d8fe45faeda26b4dc07b7dc739a347/1/_/1_10.jpg"
                    },
                    "price_range": {
                        "maximum_price": {
                            "fixed_product_taxes": [],
                            "regular_price": {
                                "currency": "AED",
                                "value": 200
                            },
                            "final_price": {
                                "currency": "AED",
                                "value": 200
                            },
                            "discount": {
                                "amount_off": 0,
                                "percent_off": 0
                            }
                        },
                        "minimum_price": {
                            "fixed_product_taxes": [],
                            "regular_price": {
                                "currency": "AED",
                                "value": 200
                            },
                            "final_price": {
                                "currency": "AED",
                                "value": 200
                            },
                            "discount": {
                                "amount_off": 0,
                                "percent_off": 0
                            }
                        }
                    }
                }
            ]
        }
    }
}